uncalled/__init__.py
uncalled/__main__.py
uncalled/ast_finder.py
uncalled/iterative.py
uncalled/regex_finder.py
uncalled/single_pass.py
uncalled/whitelist.py
uncalled-0.1.8.dist-info/LICENSE
uncalled-0.1.8.dist-info/METADATA
uncalled-0.1.8.dist-info/WHEEL
uncalled-0.1.8.dist-info/entry_points.txt
uncalled-0.1.8.dist-info/top_level.txt
uncalled-0.1.8.dist-info/RECORD
