Metadata-Version: 2.1
Name: uncalled
Version: 0.1.8
Summary: Find unused functions in Python projects
Author-email: Elazar Gershuni <elazarg@gmail.com>
License: Copyright 2023 Elazar Gershuni elazarg@gmail.com
Project-URL: Homepage, https://github.com/elazarg/uncalled
Project-URL: Bug Tracker, https://github.com/elazarg/uncalled/issues
Classifier: Programming Language :: Python :: 3
Classifier: License :: OSI Approved :: MIT License
Classifier: Operating System :: OS Independent
Requires-Python: >=3.10
License-File: LICENSE
